clusterprocess_ss_abp/__init__.py
clusterprocess_ss_abp/find_missing_numbers.py
clusterprocess_ss_abp/process_histos.py
clusterprocess_ss_abp/process_logs.py
clusterprocess_ss_abp-0.0.7.dist-info/METADATA
clusterprocess_ss_abp-0.0.7.dist-info/WHEEL
clusterprocess_ss_abp-0.0.7.dist-info/top_level.txt
clusterprocess_ss_abp-0.0.7.dist-info/RECORD
