Metadata-Version: 2.1
Name: clusterprocess-ss-abp
Version: 0.0.7
Summary: package to process LAMMPS data
Home-page: https://github.com/samueljmcameron/clusterprocess_ss_abp
Author: Sam Cameron
Author-email: samuel.j.m.cameron@gmail.com
License: UNKNOWN
Platform: UNKNOWN
Classifier: Programming Language :: Python :: 3
Classifier: License :: OSI Approved :: GNU General Public License v3 (GPLv3)
Classifier: Operating System :: OS Independent
Requires-Python: >=3.3
Requires-Dist: numpy
Requires-Dist: lammpstools
